Metadata-Version: 1.0
Name: hinomaru
Version: 0.0.1.dev0
Summary: useful library
Home-page: http://katolele.net/
Author: Katolele
Author-email: katolele@katolele.net
License: GPL
Platform: UNKNOWN
